negative_voltage_gen.v
// Negative Voltage Generating Circuit with signed Vneg

// Charge Pump Module with signed output
module ChargePump(
    input clk, reset,
    output reg signed [15:0] Vneg
);
    always @(posedge clk or posedge reset) begin
        if (reset)
            Vneg <= 16'sd0; // Start at 0V
        else if (Vneg > -16'sd32000)
            Vneg <= Vneg - 16'sd100; // Simulate stepwise drop to negative
        else
            Vneg <= -16'sd32000; // Clamp to -32000
    end
endmodule

// Current Mirror Module (threshold for turning Iout ON)
module CurrentMirror(
    input signed [15:0] Vneg,
    output reg Iout
);
    always @(*) begin
        if (Vneg < -16'sd10000) // When it's sufficiently negative
            Iout = 1;
        else
            Iout = 0;
    end
endmodule

// Top-Level Module
module NegativeVoltageGen(
    input clk, reset,
    output Iout,
    output signed [15:0] Vneg
);
    ChargePump cp (
        .clk(clk),
        .reset(reset),
        .Vneg(Vneg)
    );

    CurrentMirror cm (
        .Vneg(Vneg),
        .Iout(Iout)
    );
endmodule

testbench3.v
`timescale 1ns/1ps

module Testbench3();
    reg clk, reset;
    wire Iout;
    wire [15:0] Vneg;

    NegativeVoltageGen uut (
        .clk(clk),
        .reset(reset),
        .Iout(Iout),
        .Vneg(Vneg)
    );

    // Fast clock: 3ns toggle simulates rapid operation
    always #3 clk = ~clk;

    initial begin
        clk = 0;
        reset = 1;
        #10 reset = 0;
        #250 $finish;
    end

    initial begin
        $dumpfile("testbench3.vcd");
        $dumpvars(0, Testbench3);
        $display("Time\tclk\treset\tIout\tVneg");
        $monitor("%0t\t%b\t%b\t%b\t%d", $time, clk, reset, Iout, Vneg);
    end
endmodule

testbench3.vcd
$date
	Mon May 12 08:06:57 2025
$end
$version
	Icarus Verilog
$end
$timescale
	1ps
$end
$scope module Testbench3 $end
$var wire 1 ! Iout $end
$var wire 16 " Vneg [15:0] $end
$var reg 1 # clk $end
$var reg 1 $ reset $end
$scope module uut $end
$var wire 1 ! Iout $end
$var wire 16 % Vneg [15:0] $end
$var wire 1 & clk $end
$var wire 1 ' reset $end
$scope module cp $end
$var wire 1 & clk $end
$var wire 1 ' reset $end
$var reg 16 ( Vneg [15:0] $end
$upscope $end
$scope module cm $end
$var wire 16 ) Vneg [15:0] $end
$var reg 1 * Iout $end
$upscope $end
$upscope $end
$upscope $end
$enddefinitions $end
#0
$dumpvars
0*
b0 )
b0 (
1'
0&
b0 %
1$
0#
b0 "
0!
$end
#3000
1#
1&
#6000
0#
0&
#9000
1#
1&
#10000
0$
0'
#12000
0#
0&
#15000
b1111111110011100 (
b1111111110011100 "
b1111111110011100 %
b1111111110011100 )
1#
1&
#18000
0#
0&
#21000
b1111111100111000 (
b1111111100111000 "
b1111111100111000 %
b1111111100111000 )
1#
1&
#24000
0#
0&
#27000
b1111111011010100 (
b1111111011010100 "
b1111111011010100 %
b1111111011010100 )
1#
1&
#30000
0#
0&
#33000
b1111111001110000 (
b1111111001110000 "
b1111111001110000 %
b1111111001110000 )
1#
1&
#36000
0#
0&
#39000
b1111111000001100 (
b1111111000001100 "
b1111111000001100 %
b1111111000001100 )
1#
1&
#42000
0#
0&
#45000
b1111110110101000 (
b1111110110101000 "
b1111110110101000 %
b1111110110101000 )
1#
1&
#48000
0#
0&
#51000
b1111110101000100 (
b1111110101000100 "
b1111110101000100 %
b1111110101000100 )
1#
1&
#54000
0#
0&
#57000
b1111110011100000 (
b1111110011100000 "
b1111110011100000 %
b1111110011100000 )
1#
1&
#60000
0#
0&
#63000
b1111110001111100 (
b1111110001111100 "
b1111110001111100 %
b1111110001111100 )
1#
1&
#66000
0#
0&
#69000
b1111110000011000 (
b1111110000011000 "
b1111110000011000 %
b1111110000011000 )
1#
1&
#72000
0#
0&
#75000
b1111101110110100 (
b1111101110110100 "
b1111101110110100 %
b1111101110110100 )
1#
1&
#78000
0#
0&
#81000
b1111101101010000 (
b1111101101010000 "
b1111101101010000 %
b1111101101010000 )
1#
1&
#84000
0#
0&
#87000
b1111101011101100 (
b1111101011101100 "
b1111101011101100 %
b1111101011101100 )
1#
1&
#90000
0#
0&
#93000
b1111101010001000 (
b1111101010001000 "
b1111101010001000 %
b1111101010001000 )
1#
1&
#96000
0#
0&
#99000
b1111101000100100 (
b1111101000100100 "
b1111101000100100 %
b1111101000100100 )
1#
1&
#102000
0#
0&
#105000
b1111100111000000 (
b1111100111000000 "
b1111100111000000 %
b1111100111000000 )
1#
1&
#108000
0#
0&
#111000
b1111100101011100 (
b1111100101011100 "
b1111100101011100 %
b1111100101011100 )
1#
1&
#114000
0#
0&
#117000
b1111100011111000 (
b1111100011111000 "
b1111100011111000 %
b1111100011111000 )
1#
1&
#120000
0#
0&
#123000
b1111100010010100 (
b1111100010010100 "
b1111100010010100 %
b1111100010010100 )
1#
1&
#126000
0#
0&
#129000
b1111100000110000 (
b1111100000110000 "
b1111100000110000 %
b1111100000110000 )
1#
1&
#132000
0#
0&
#135000
b1111011111001100 (
b1111011111001100 "
b1111011111001100 %
b1111011111001100 )
1#
1&
#138000
0#
0&
#141000
b1111011101101000 (
b1111011101101000 "
b1111011101101000 %
b1111011101101000 )
1#
1&
#144000
0#
0&
#147000
b1111011100000100 (
b1111011100000100 "
b1111011100000100 %
b1111011100000100 )
1#
1&
#150000
0#
0&
#153000
b1111011010100000 (
b1111011010100000 "
b1111011010100000 %
b1111011010100000 )
1#
1&
#156000
0#
0&
#159000
b1111011000111100 (
b1111011000111100 "
b1111011000111100 %
b1111011000111100 )
1#
1&
#162000
0#
0&
#165000
b1111010111011000 (
b1111010111011000 "
b1111010111011000 %
b1111010111011000 )
1#
1&
#168000
0#
0&
#171000
b1111010101110100 (
b1111010101110100 "
b1111010101110100 %
b1111010101110100 )
1#
1&
#174000
0#
0&
#177000
b1111010100010000 (
b1111010100010000 "
b1111010100010000 %
b1111010100010000 )
1#
1&
#180000
0#
0&
#183000
b1111010010101100 (
b1111010010101100 "
b1111010010101100 %
b1111010010101100 )
1#
1&
#186000
0#
0&
#189000
b1111010001001000 (
b1111010001001000 "
b1111010001001000 %
b1111010001001000 )
1#
1&
#192000
0#
0&
#195000
b1111001111100100 (
b1111001111100100 "
b1111001111100100 %
b1111001111100100 )
1#
1&
#198000
0#
0&
#201000
b1111001110000000 (
b1111001110000000 "
b1111001110000000 %
b1111001110000000 )
1#
1&
#204000
0#
0&
#207000
b1111001100011100 (
b1111001100011100 "
b1111001100011100 %
b1111001100011100 )
1#
1&
#210000
0#
0&
#213000
b1111001010111000 (
b1111001010111000 "
b1111001010111000 %
b1111001010111000 )
1#
1&
#216000
0#
0&
#219000
b1111001001010100 (
b1111001001010100 "
b1111001001010100 %
b1111001001010100 )
1#
1&
#222000
0#
0&
#225000
b1111000111110000 (
b1111000111110000 "
b1111000111110000 %
b1111000111110000 )
1#
1&
#228000
0#
0&
#231000
b1111000110001100 (
b1111000110001100 "
b1111000110001100 %
b1111000110001100 )
1#
1&
#234000
0#
0&
#237000
b1111000100101000 (
b1111000100101000 "
b1111000100101000 %
b1111000100101000 )
1#
1&
#240000
0#
0&
#243000
b1111000011000100 (
b1111000011000100 "
b1111000011000100 %
b1111000011000100 )
1#
1&
#246000
0#
0&
#249000
b1111000001100000 (
b1111000001100000 "
b1111000001100000 %
b1111000001100000 )
1#
1&
#252000
0#
0&
#255000
b1110111111111100 (
b1110111111111100 "
b1110111111111100 %
b1110111111111100 )
1#
1&
