negative_voltage_gen.v
// Negative Voltage Generating Circuit with signed Vneg

// Charge Pump Module with signed output
module ChargePump(
    input clk, reset,
    output reg signed [15:0] Vneg
);
    always @(posedge clk or posedge reset) begin
        if (reset)
            Vneg <= 16'sd0; // Start at 0V
        else if (Vneg > -16'sd32000)
            Vneg <= Vneg - 16'sd100; // Simulate stepwise drop to negative
        else
            Vneg <= -16'sd32000; // Clamp to -32000
    end
endmodule

// Current Mirror Module (threshold for turning Iout ON)
module CurrentMirror(
    input signed [15:0] Vneg,
    output reg Iout
);
    always @(*) begin
        if (Vneg < -16'sd10000) // When it's sufficiently negative
            Iout = 1;
        else
            Iout = 0;
    end
endmodule

// Top-Level Module
module NegativeVoltageGen(
    input clk, reset,
    output Iout,
    output signed [15:0] Vneg
);
    ChargePump cp (
        .clk(clk),
        .reset(reset),
        .Vneg(Vneg)
    );

    CurrentMirror cm (
        .Vneg(Vneg),
        .Iout(Iout)
    );
endmodule

testbench1.v
`timescale 1ns/1ps

module Testbench1();
    reg clk, reset;
    wire Iout;
    wire [15:0] Vneg;

    // Connect to DUT
    NegativeVoltageGen uut (
        .clk(clk),
        .reset(reset),
        .Iout(Iout),
        .Vneg(Vneg)
    );

    // Clock generation
    always #5 clk = ~clk;

    // Initialization
    initial begin
        clk = 0;
        reset = 1;
        #10 reset = 0;
        #100 $finish;
    end

    // Output monitoring
    initial begin
        $dumpfile("testbench1.vcd");
        $dumpvars(0, Testbench1);
        $display("Time\tclk\treset\tIout\tVneg");
        $monitor("%0t\t%b\t%b\t%b\t%d", $time, clk, reset, Iout, Vneg);
    end
endmodule

testbench1.vcd
$date
	Mon May 12 08:02:08 2025
$end
$version
	Icarus Verilog
$end
$timescale
	1ps
$end
$scope module Testbench1 $end
$var wire 1 ! Iout $end
$var wire 16 " Vneg [15:0] $end
$var reg 1 # clk $end
$var reg 1 $ reset $end
$scope module uut $end
$var wire 1 ! Iout $end
$var wire 16 % Vneg [15:0] $end
$var wire 1 & clk $end
$var wire 1 ' reset $end
$scope module cp $end
$var wire 1 & clk $end
$var wire 1 ' reset $end
$var reg 16 ( Vneg [15:0] $end
$upscope $end
$scope module cm $end
$var wire 16 ) Vneg [15:0] $end
$var reg 1 * Iout $end
$upscope $end
$upscope $end
$upscope $end
$enddefinitions $end
#0
$dumpvars
0*
b0 )
b0 (
1'
0&
b0 %
1$
0#
b0 "
0!
$end
#5000
1#
1&
#10000
0#
0&
0$
0'
#15000
b1111111110011100 (
b1111111110011100 "
b1111111110011100 %
b1111111110011100 )
1#
1&
#20000
0#
0&
#25000
b1111111100111000 (
b1111111100111000 "
b1111111100111000 %
b1111111100111000 )
1#
1&
#30000
0#
0&
#35000
b1111111011010100 (
b1111111011010100 "
b1111111011010100 %
b1111111011010100 )
1#
1&
#40000
0#
0&
#45000
b1111111001110000 (
b1111111001110000 "
b1111111001110000 %
b1111111001110000 )
1#
1&
#50000
0#
0&
#55000
b1111111000001100 (
b1111111000001100 "
b1111111000001100 %
b1111111000001100 )
1#
1&
#60000
0#
0&
#65000
b1111110110101000 (
b1111110110101000 "
b1111110110101000 %
b1111110110101000 )
1#
1&
#70000
0#
0&
#75000
b1111110101000100 (
b1111110101000100 "
b1111110101000100 %
b1111110101000100 )
1#
1&
#80000
0#
0&
#85000
b1111110011100000 (
b1111110011100000 "
b1111110011100000 %
b1111110011100000 )
1#
1&
#90000
0#
0&
#95000
b1111110001111100 (
b1111110001111100 "
b1111110001111100 %
b1111110001111100 )
1#
1&
#100000
0#
0&
#105000
b1111110000011000 (
b1111110000011000 "
b1111110000011000 %
b1111110000011000 )
1#
1&
