negative_voltage_gen.v
// Negative Voltage Generating Circuit with signed Vneg

// Charge Pump Module with signed output
module ChargePump(
    input clk, reset,
    output reg signed [15:0] Vneg
);
    always @(posedge clk or posedge reset) begin
        if (reset)
            Vneg <= 16'sd0; // Start at 0V
        else if (Vneg > -16'sd32000)
            Vneg <= Vneg - 16'sd100; // Simulate stepwise drop to negative
        else
            Vneg <= -16'sd32000; // Clamp to -32000
    end
endmodule

// Current Mirror Module (threshold for turning Iout ON)
module CurrentMirror(
    input signed [15:0] Vneg,
    output reg Iout
);
    always @(*) begin
        if (Vneg < -16'sd10000) // When it's sufficiently negative
            Iout = 1;
        else
            Iout = 0;
    end
endmodule

// Top-Level Module
module NegativeVoltageGen(
    input clk, reset,
    output Iout,
    output signed [15:0] Vneg
);
    ChargePump cp (
        .clk(clk),
        .reset(reset),
        .Vneg(Vneg)
    );

    CurrentMirror cm (
        .Vneg(Vneg),
        .Iout(Iout)
    );
endmodule

testbench2.v
`timescale 1ns/1ps

module Testbench2();
    reg clk, reset;
    wire Iout;
    wire [15:0] Vneg;

    NegativeVoltageGen uut (
        .clk(clk),
        .reset(reset),
        .Iout(Iout),
        .Vneg(Vneg)
    );

    // Clock with slightly slower toggle to simulate delay
    always #7 clk = ~clk;

    initial begin
        clk = 0;
        reset = 1;
        #10 reset = 0;
        #200 $finish;
    end

    initial begin
        $dumpfile("testbench2.vcd");
        $dumpvars(0, Testbench2);
        $display("Time\tclk\treset\tIout\tVneg");
        $monitor("%0t\t%b\t%b\t%b\t%d", $time, clk, reset, Iout, Vneg);
    end
endmodule

testbench2.vcd
$date
	Mon May 12 08:07:12 2025
$end
$version
	Icarus Verilog
$end
$timescale
	1ps
$end
$scope module Testbench2 $end
$var wire 1 ! Iout $end
$var wire 16 " Vneg [15:0] $end
$var reg 1 # clk $end
$var reg 1 $ reset $end
$scope module uut $end
$var wire 1 ! Iout $end
$var wire 16 % Vneg [15:0] $end
$var wire 1 & clk $end
$var wire 1 ' reset $end
$scope module cp $end
$var wire 1 & clk $end
$var wire 1 ' reset $end
$var reg 16 ( Vneg [15:0] $end
$upscope $end
$scope module cm $end
$var wire 16 ) Vneg [15:0] $end
$var reg 1 * Iout $end
$upscope $end
$upscope $end
$upscope $end
$enddefinitions $end
#0
$dumpvars
0*
b0 )
b0 (
1'
0&
b0 %
1$
0#
b0 "
0!
$end
#7000
1#
1&
#10000
0$
0'
#14000
0#
0&
#21000
b1111111110011100 (
b1111111110011100 "
b1111111110011100 %
b1111111110011100 )
1#
1&
#28000
0#
0&
#35000
b1111111100111000 (
b1111111100111000 "
b1111111100111000 %
b1111111100111000 )
1#
1&
#42000
0#
0&
#49000
b1111111011010100 (
b1111111011010100 "
b1111111011010100 %
b1111111011010100 )
1#
1&
#56000
0#
0&
#63000
b1111111001110000 (
b1111111001110000 "
b1111111001110000 %
b1111111001110000 )
1#
1&
#70000
0#
0&
#77000
b1111111000001100 (
b1111111000001100 "
b1111111000001100 %
b1111111000001100 )
1#
1&
#84000
0#
0&
#91000
b1111110110101000 (
b1111110110101000 "
b1111110110101000 %
b1111110110101000 )
1#
1&
#98000
0#
0&
#105000
b1111110101000100 (
b1111110101000100 "
b1111110101000100 %
b1111110101000100 )
1#
1&
#112000
0#
0&
#119000
b1111110011100000 (
b1111110011100000 "
b1111110011100000 %
b1111110011100000 )
1#
1&
#126000
0#
0&
#133000
b1111110001111100 (
b1111110001111100 "
b1111110001111100 %
b1111110001111100 )
1#
1&
#140000
0#
0&
#147000
b1111110000011000 (
b1111110000011000 "
b1111110000011000 %
b1111110000011000 )
1#
1&
#154000
0#
0&
#161000
b1111101110110100 (
b1111101110110100 "
b1111101110110100 %
b1111101110110100 )
1#
1&
#168000
0#
0&
#175000
b1111101101010000 (
b1111101101010000 "
b1111101101010000 %
b1111101101010000 )
1#
1&
#182000
0#
0&
#189000
b1111101011101100 (
b1111101011101100 "
b1111101011101100 %
b1111101011101100 )
1#
1&
#196000
0#
0&
#203000
b1111101010001000 (
b1111101010001000 "
b1111101010001000 %
b1111101010001000 )
1#
1&
